compspec_flux/__init__.py
compspec_flux/defaults.py
compspec_flux/nodelist.py
compspec_flux/plugin.py
compspec_flux/version.py
compspec_flux-0.0.11.dist-info/LICENSE
compspec_flux-0.0.11.dist-info/METADATA
compspec_flux-0.0.11.dist-info/NOTICE
compspec_flux-0.0.11.dist-info/WHEEL
compspec_flux-0.0.11.dist-info/top_level.txt
compspec_flux-0.0.11.dist-info/RECORD
